discosub/__init__.py
discosub/main.py
discosub/runner.py
discosub/commands/__init__.py
discosub/commands/discover/__init__.py
discosub/core/__init__.py
discosub/core/profil.py
discosub/core/ui.py
discosub/dictionaries/__init__.py
discosub/dictionaries/agressive.py
discosub/dictionaries/essential.py
discosub-0.3.0.dist-info/DESCRIPTION.rst
discosub-0.3.0.dist-info/METADATA
discosub-0.3.0.dist-info/RECORD
discosub-0.3.0.dist-info/WHEEL
discosub-0.3.0.dist-info/entry_points.txt
discosub-0.3.0.dist-info/metadata.json
discosub-0.3.0.dist-info/top_level.txt
