Metadata-Version: 2.0
Name: discosub
Version: 0.3.0
Summary: Simple, Faster, & Efficient, Subdomain Discovery Scanner
Home-page: https://4383.github.io/discosub/
Author: Hervé Beraud
Author-email: herveberaud.pro@gmail.com
License: GNU General Public License v3
Keywords: discosub
Platform: UNKNOWN
Classifier: Development Status :: 3 - Alpha
Classifier: Intended Audience :: Developers
Classifier: Intended Audience :: System Administrators
Classifier: Intended Audience :: Information Technology
Classifier: License :: OSI Approved :: GNU General Public License v3 or later (GPLv3+)
Classifier: Natural Language :: English
Classifier: Programming Language :: Python :: 2
Classifier: Programming Language :: Python :: 2.6
Classifier: Programming Language :: Python :: 2.7
Classifier: Programming Language :: Python :: 3
Classifier: Programming Language :: Python :: 3.3
Classifier: Programming Language :: Python :: 3.4
Classifier: Programming Language :: Python :: 3.5
Classifier: Environment :: Console
Classifier: Topic :: Security
Classifier: Topic :: Utilities
Requires-Dist: click
